AUTHORS.rst
CONTRIBUTING.rst
HISTORY.rst
LICENSE
MANIFEST.in
README.rst
setup.cfg
setup.py
ceek/__init__.py
ceek/ceek.py
ceek.egg-info/PKG-INFO
ceek.egg-info/SOURCES.txt
ceek.egg-info/dependency_links.txt
ceek.egg-info/not-zip-safe
ceek.egg-info/top_level.txt
docs/Makefile
docs/authors.rst
docs/conf.py
docs/contributing.rst
docs/history.rst
docs/index.rst
docs/installation.rst
docs/make.bat
docs/readme.rst
docs/usage.rst
tests/__init__.py
tests/test_ceek.py