Metadata-Version: 1.1
Name: ceek
Version: 0.1.3
Summary: ceek python client
Home-page: https://github.com/ceekio/ceek-python
Author: team@ceek.io
Author-email: team@ceek.io
License: BSD
Keywords: ceek
Platform: UNKNOWN
Classifier: Development Status :: 2 - Pre-Alpha
Classifier: Intended Audience :: Developers
Classifier: License :: OSI Approved :: BSD License
Classifier: Natural Language :: English
Classifier: Programming Language :: Python :: 2
Classifier: Programming Language :: Python :: 2.6
Classifier: Programming Language :: Python :: 2.7
Classifier: Programming Language :: Python :: 3
Classifier: Programming Language :: Python :: 3.3
Classifier: Programming Language :: Python :: 3.4
